LICENSE
README.md
pipevcr
pipevcr.py
setup.py
pipevcr.egg-info/PKG-INFO
pipevcr.egg-info/SOURCES.txt
pipevcr.egg-info/dependency_links.txt
pipevcr.egg-info/top_level.txt