Metadata-Version: 2.4
Name: pipevcr
Version: 0.1.2
Summary: Record and play back pipes.
Home-page: https://github.com/laktak/pipevcr
Author: Christian Zangl
Author-email: laktak@cdak.net
License-File: LICENSE
Dynamic: author
Dynamic: author-email
Dynamic: description
Dynamic: description-content-type
Dynamic: home-page
Dynamic: license-file
Dynamic: summary
